odoo/addons/calendar_event_link_base/README.rst
odoo/addons/calendar_event_link_base/__init__.py
odoo/addons/calendar_event_link_base/__manifest__.py
odoo/addons/calendar_event_link_base/i18n/calendar_event_link_base.pot
odoo/addons/calendar_event_link_base/models/__init__.py
odoo/addons/calendar_event_link_base/models/calendar_event_link_mixin.py
odoo/addons/calendar_event_link_base/readme/CONTRIBUTORS.rst
odoo/addons/calendar_event_link_base/readme/DESCRIPTION.rst
odoo/addons/calendar_event_link_base/readme/USAGE.rst
odoo/addons/calendar_event_link_base/static/description/icon.png
odoo/addons/calendar_event_link_base/static/description/index.html
odoo12_addon_calendar_event_link_base-12.0.1.0.0.99.dev6.dist-info/METADATA
odoo12_addon_calendar_event_link_base-12.0.1.0.0.99.dev6.dist-info/WHEEL
odoo12_addon_calendar_event_link_base-12.0.1.0.0.99.dev6.dist-info/top_level.txt
odoo12_addon_calendar_event_link_base-12.0.1.0.0.99.dev6.dist-info/RECORD
