Metadata-Version: 2.1
Name: odoo12-addon-calendar-event-link-base
Version: 12.0.1.0.0.99.dev6
Summary: This module add an abstract model that provide an action to link any model to calendar events
Home-page: https://github.com/OCA/calendar
Author: ACSONE SA/NV,Odoo Community Association (OCA)
Author-email: support@odoo-community.org
License: AGPL-3
Platform: UNKNOWN
Classifier: Programming Language :: Python
Classifier: Framework :: Odoo
Classifier: Framework :: Odoo :: 12.0
Classifier: License :: OSI Approved :: GNU Affero General Public License v3
Requires-Python: >=3.5
Requires-Dist: odoo <12.1dev,>=12.0a
